{"id": 2829, "artista": "Foreign Objects", "album": "Violent World LP (Rave Up)", "año": 2002, "portada": "https://i.discogs.com/b7AHpf9Z2KRTbzZ3W-hLQ8eTXmpSMBGB925z-t-Rcxg/rs:fit/g:sm/q:90/h:400/w:400/czM6Ly9kaXNjb2dz/LWRhdGFiYXNlLWlt/YWdlcy9SLTMxOTQ1/NjktMTMxOTk3NDk2/MC5qcGVn.jpeg", "generos": ["Rock"], "estilos": ["Garage Rock", "Hard Rock", "Punk"], "pais": "Italy", "discogs_id": 3194569, "tracks": [{"num": 1, "titulo": "Not Too Cool + Sgt. Sanders", "duracion": 328, "videoId": null}, {"num": 2, "titulo": "I Am A Dog", "duracion": 76, "videoId": "9EP_u8yVfSQ"}, {"num": 3, "titulo": "Lose Some Weight", "duracion": 128, "videoId": "riryR3HvESY"}, {"num": 4, "titulo": "Speak English", "duracion": 151, "videoId": null}, {"num": 5, "titulo": "Collect Checks", "duracion": 190, "videoId": null}, {"num": 6, "titulo": "Buy A Car", "duracion": 129, "videoId": null}, {"num": 7, "titulo": "Plan Nine", "duracion": 152, "videoId": "EoUCIx2-XAc"}, {"num": 8, "titulo": "You Go Home", "duracion": 404, "videoId": "D_jazchrPkA"}, {"num": 9, "titulo": "Wrestling Is Real", "duracion": 165, "videoId": "gKLx4q3oacI"}, {"num": 10, "titulo": "It's A Jay", "duracion": 190, "videoId": null}, {"num": 11, "titulo": "Recycled Jizz", "duracion": 194, "videoId": null}, {"num": 12, "titulo": "Violent World", "duracion": 152, "videoId": "SqDSyzXfdFE"}, {"num": 13, "titulo": "Capture The Clingones", "duracion": 188, "videoId": null}, {"num": 14, "titulo": "Now She's Dead", "duracion": 209, "videoId": null}, {"num": 15, "titulo": "Television Wizard", "duracion": 331, "videoId": "xX6rrALCK6M"}, {"num": 16, "titulo": "Genius Of Lou Albano", "duracion": 102, "videoId": null}]}