{"id": 2856, "artista": "Foyone", "album": "Rico Sin Denuncia", "año": 2017, "portada": "https://i.discogs.com/x3nzShOM2a1IKs8lvkAU2x8AySW1upGOgCh9CwyQ7No/rs:fit/g:sm/q:90/h:540/w:541/czM6Ly9kaXNjb2dz/LWRhdGFiYXNlLWlt/YWdlcy9SLTEzOTYw/NzcxLTE1NjQ5NTg4/NzEtNTcwNy5wbmc.jpeg", "generos": ["Hip Hop"], "estilos": ["Hardcore Hip-Hop", "Gangsta"], "pais": "Spain", "discogs_id": 13960771, "tracks": [{"num": 1, "titulo": "Volver", "duracion": 182, "videoId": "HCyRF6eFmF0"}, {"num": 2, "titulo": "Guerrero psicodélico", "duracion": 340, "videoId": "g17WalO4Ky8"}, {"num": 3, "titulo": "Aviso Maternal", "duracion": 208, "videoId": "QAb1WaUTHpQ"}, {"num": 4, "titulo": "Atupetra", "duracion": 231, "videoId": "wA9no8_Rrzo"}, {"num": 5, "titulo": "Atraco del 97", "duracion": 178, "videoId": "kUW0amVC9LQ"}, {"num": 6, "titulo": "Ni carne ni hueso", "duracion": 193, "videoId": "OLLuXy8EJeA"}, {"num": 7, "titulo": "Robótica generación", "duracion": 250, "videoId": "9fEdPy8VnUg"}, {"num": 8, "titulo": "Ídolos de plástico", "duracion": 201, "videoId": "hVKBhyF8BGc"}, {"num": 9, "titulo": "El tercer gemelo", "duracion": 180, "videoId": "JlbdPk2IhSA"}, {"num": 10, "titulo": "El día del chuletón", "duracion": 170, "videoId": "_HhT3zFZWtk"}, {"num": 11, "titulo": "Su culito", "duracion": 205, "videoId": "5vK1akGPgZc"}, {"num": 12, "titulo": "Óxido", "duracion": 188, "videoId": "5bgSG73eyQs"}, {"num": 13, "titulo": "Rico sin denuncia", "duracion": 190, "videoId": "uNImSsKvasg"}, {"num": 14, "titulo": "Ciudad del vicio (Remix)", "duracion": 141, "videoId": "mL3QW2ct8Vg"}]}