{"id": 8320, "artista": "The Long Ryders", "album": "Native Sons", "año": 1984, "portada": "https://i.discogs.com/G1cO7vqPD4AqeJ16CLXA4Nr_DrbYABYkrJj9y266XrU/rs:fit/g:sm/q:90/h:597/w:600/czM6Ly9kaXNjb2dz/LWRhdGFiYXNlLWlt/YWdlcy9SLTE2MTg0/OTk1LTE3Mjk0OTky/NjctOTM2Ny5qcGVn.jpeg", "generos": ["Rock", "Folk, World, & Country"], "estilos": null, "pais": "Japan", "discogs_id": 16184995, "tracks": [{"num": 1, "titulo": "Final Wild Son", "duracion": 155, "videoId": "VD2DpYZLGbo"}, {"num": 2, "titulo": "Still Get By", "duracion": 170, "videoId": "3qwJaF-Y-sc"}, {"num": 3, "titulo": "Ivory Tower", "duracion": 181, "videoId": "gddFTqmQ1BI"}, {"num": 4, "titulo": "Run Dusty Run", "duracion": 147, "videoId": "E6baGpOSN-I"}, {"num": 5, "titulo": "(Sweet) Mental Revenge", "duracion": 171, "videoId": "tFKU04TvLME"}, {"num": 6, "titulo": "Fair Game", "duracion": 158, "videoId": "hRY3_fA1OkE"}, {"num": 7, "titulo": "Tell It to the Judge on Sunday", "duracion": 187, "videoId": "PzGk0_JPe8o"}, {"num": 8, "titulo": "Wreck of the 809", "duracion": 236, "videoId": "Iqx-2w0nQnM"}, {"num": 9, "titulo": "Too Close to the Light", "duracion": 251, "videoId": "JYWPomkCB-Y"}, {"num": 10, "titulo": "Never Got to Meet the Mom", "duracion": 136, "videoId": "Q89l2LWx4Kw"}, {"num": 11, "titulo": "I Had a Dream", "duracion": 233, "videoId": "mdlZYrtRsaU"}]}