{"id": 2070, "artista": "David Bowie", "album": "Best of Bowie", "año": 2002, "portada": null, "generos": null, "estilos": null, "pais": null, "discogs_id": null, "tracks": [{"num": 1, "titulo": "Space Oddity", "duracion": 314, "videoId": null}, {"num": 1, "titulo": "Sound and Vision", "duracion": 186, "videoId": null}, {"num": 2, "titulo": "The Man Who Sold the World", "duracion": 238, "videoId": null}, {"num": 2, "titulo": "“Heroes”", "duracion": 217, "videoId": null}, {"num": 3, "titulo": "Oh! You Pretty Things", "duracion": 194, "videoId": null}, {"num": 3, "titulo": "Boys Keep Swinging", "duracion": 199, "videoId": null}, {"num": 4, "titulo": "Changes", "duracion": 214, "videoId": null}, {"num": 5, "titulo": "Life on Mars?", "duracion": 231, "videoId": null}, {"num": 5, "titulo": "Ashes to Ashes", "duracion": 217, "videoId": null}, {"num": 6, "titulo": "Starman", "duracion": 254, "videoId": null}, {"num": 6, "titulo": "Fashion", "duracion": 207, "videoId": null}, {"num": 7, "titulo": "Ziggy Stardust", "duracion": 193, "videoId": null}, {"num": 8, "titulo": "Let’s Dance", "duracion": 250, "videoId": null}, {"num": 9, "titulo": "John, I’m Only Dancing", "duracion": 166, "videoId": null}, {"num": 9, "titulo": "China Girl", "duracion": 259, "videoId": null}, {"num": 10, "titulo": "The Jean Genie", "duracion": 246, "videoId": null}, {"num": 10, "titulo": "Modern Love", "duracion": 239, "videoId": null}, {"num": 11, "titulo": "Drive‐In Saturday", "duracion": 270, "videoId": null}, {"num": 11, "titulo": "Blue Jean", "duracion": 192, "videoId": null}, {"num": 12, "titulo": "Sorrow", "duracion": 175, "videoId": null}, {"num": 12, "titulo": "This Is Not America", "duracion": 233, "videoId": null}, {"num": 13, "titulo": "Loving the Alien", "duracion": 286, "videoId": null}, {"num": 14, "titulo": "Rebel Rebel", "duracion": 271, "videoId": null}, {"num": 15, "titulo": "Young Americans", "duracion": 195, "videoId": null}, {"num": 15, "titulo": "Absolute Beginners", "duracion": 338, "videoId": null}, {"num": 16, "titulo": "Fame", "duracion": 257, "videoId": null}, {"num": 17, "titulo": "Golden Years", "duracion": 210, "videoId": null}, {"num": 19, "titulo": "Wild Is the Wind", "duracion": 361, "videoId": null}]}