{"id": 3279, "artista": "Guru", "album": "Jazzmatazz Volume II: The New Reality", "año": 1995, "portada": "https://lastfm.freetls.fastly.net/i/u/300x300/bc5a8d2a87e34609ac5ca66a618f4c03.jpg", "generos": ["Electronic"], "estilos": ["Acid Jazz", "Hip Hop"], "pais": "Australia", "discogs_id": 31647248, "tracks": [{"num": 1, "titulo": "Intro (Light It Up) / Jazzalude I: New Reality Style", "duracion": 106, "videoId": "n1wTvXBEUcY"}, {"num": 2, "titulo": "Lifesaver", "duracion": 255, "videoId": "UqDwvoJBfiE"}, {"num": 3, "titulo": "Living in This World", "duracion": 271, "videoId": "1WgRurG4IDM"}, {"num": 4, "titulo": "Looking Through Darkness", "duracion": 290, "videoId": "MMl4A9QOCqg"}, {"num": 5, "titulo": "Skit A (Interview) / Watch What You Say", "duracion": 305, "videoId": "6q2jvFqdPYk"}, {"num": 6, "titulo": "Jazzalude II: Defining Purpose", "duracion": 64, "videoId": "dhxMcdCmUuk"}, {"num": 7, "titulo": "For You", "duracion": 243, "videoId": "uo3QxI91Vks"}, {"num": 8, "titulo": "Insert A (Mental Relaxation) / Medicine", "duracion": 262, "videoId": "m7oY-QzWy_k"}, {"num": 9, "titulo": "Lost Souls", "duracion": 254, "videoId": "_SGlnZEkjDw"}, {"num": 10, "titulo": "Insert B (The Real Deal) / Nobody Knows", "duracion": 240, "videoId": "GQxWkRm6x0U"}, {"num": 11, "titulo": "Jazzalude III: Hip Hop as a Way of Life", "duracion": 79, "videoId": "P69-CT01wLw"}, {"num": 12, "titulo": "Respect the Architect", "duracion": 293, "videoId": "WyRxlh6EL4E"}, {"num": 13, "titulo": "Feel the Music", "duracion": 240, "videoId": "HA7wSwVQ7cU"}, {"num": 14, "titulo": "Young Ladies", "duracion": 254, "videoId": "0_nXO_lMcks"}, {"num": 15, "titulo": "The Traveler", "duracion": 243, "videoId": "Xb6Tj8P50UE"}, {"num": 16, "titulo": "Jazzalude IV: Maintaining Focus", "duracion": 80, "videoId": "3Q0fpqFOW9c"}, {"num": 17, "titulo": "Count Your Blessings", "duracion": 214, "videoId": "Ct3xKZGs2iU"}, {"num": 18, "titulo": "Choice of Weapons", "duracion": 266, "videoId": "z45AjGud6bQ"}, {"num": 19, "titulo": "Something in the Past", "duracion": 201, "videoId": "f9eI0Wz72VI"}, {"num": 20, "titulo": "Skit B (Alot on My Mind) / Revelation", "duracion": 276, "videoId": "j3lci7F8n6c"}]}