{"id": 11230, "artista": "Yo La Tengo", "album": "Im Not Afraid Of You And I Will Beat Your Ass", "año": 2006, "portada": "https://i.discogs.com/Ghf4pyi6XBYxYyqvHO9b2F1yx0r7V63wQ9QJtZ8AZWg/rs:fit/g:sm/q:90/h:600/w:600/czM6Ly9kaXNjb2dz/LWRhdGFiYXNlLWlt/YWdlcy9SLTU2NDQ4/NTEtMTYxODczOTgy/OC03MTcwLmpwZWc.jpeg", "generos": ["Rock"], "estilos": ["Indie Rock"], "pais": "UK", "discogs_id": 5644851, "tracks": [{"num": 1, "titulo": "Pass The Hatchet", "duracion": 588, "videoId": "3ngROr7CZ8c"}, {"num": 2, "titulo": "Beanbag Chair", "duracion": 122, "videoId": null}, {"num": 3, "titulo": "I Feel Like Going Home", "duracion": 194, "videoId": "eOeczVwyQiE"}, {"num": 4, "titulo": "Mr Tough", "duracion": 186, "videoId": "tlGCx3tzIz0"}, {"num": 5, "titulo": "Black Flowers", "duracion": 208, "videoId": "7rDgU2A_Mlk"}, {"num": 6, "titulo": "The Race Is On Again", "duracion": 217, "videoId": "_Fx8vqsyxwA"}, {"num": 7, "titulo": "The Room Got Heavy", "duracion": 250, "videoId": "yKzOBrauTks"}, {"num": 8, "titulo": "Sometimes I Dont Get You", "duracion": 136, "videoId": "RuSz4JY8u-g"}, {"num": 9, "titulo": "Instrumental", "duracion": 471, "videoId": null}, {"num": 10, "titulo": "I Shouldve Known Better", "duracion": 137, "videoId": "YxlqclPKF2Q"}, {"num": 11, "titulo": "Ronnie", "duracion": 121, "videoId": "WrEU6vd3-G8"}, {"num": 12, "titulo": "The Weakest Part", "duracion": 124, "videoId": "4sg5DtTpAXg"}, {"num": 13, "titulo": "Tonight", "duracion": 162, "videoId": null}, {"num": 14, "titulo": "Happiness Is A Warm Gun", "duracion": 196, "videoId": "vdvnOH060Qg"}, {"num": 15, "titulo": "The Story Of", "duracion": 648, "videoId": "z5Mm4xYgZg4"}]}