{"id": 3497, "artista": "Ingrid Lucia and The Flying Neutrinos", "album": "I'd Rather Be in New Orleans", "año": 1994, "portada": "https://i.discogs.com/agPDj67jmnYtdj9dozIQfuAQ-yD5_cAb5OgoYyJ-9Qg/rs:fit/g:sm/q:90/h:595/w:600/czM6Ly9kaXNjb2dz/LWRhdGFiYXNlLWlt/YWdlcy9SLTgyMjE2/ODAtMTQ1NzkxMjc4/NS0yMDAwLmpwZWc.jpeg", "generos": ["Jazz"], "estilos": ["Dixieland", "Louisiana Blues", "Swing"], "pais": "US", "discogs_id": 8221680, "tracks": [{"num": 1, "titulo": "Delta Bound", "duracion": 363, "videoId": "XZR-rGkIMa4"}, {"num": 2, "titulo": "Barbarin's Second Line", "duracion": 410, "videoId": "39_eg-lE8sQ"}, {"num": 3, "titulo": "Streetlight", "duracion": 274, "videoId": "GMHiBS3sRpU"}, {"num": 5, "titulo": "Swimming Pool Blue", "duracion": 320, "videoId": "sukkqsH-79Q"}, {"num": 6, "titulo": "Marie Laveau", "duracion": 270, "videoId": "XgYlLCh9VpY"}, {"num": 7, "titulo": "Bei mir bist Du schön", "duracion": 277, "videoId": "_A4J3-6SbAM"}, {"num": 9, "titulo": "New Dog Blues", "duracion": 473, "videoId": "ZKVCo18zatk"}, {"num": 10, "titulo": "Alone in This House", "duracion": 350, "videoId": "nJGZr9XQd4c"}, {"num": 11, "titulo": "I'm in a Hole", "duracion": 327, "videoId": "od0lSLO3g4o"}, {"num": 12, "titulo": "I'd Rather Be in New Orleans", "duracion": 211, "videoId": "WbeJzXVR7uk"}]}