{"id": 6850, "artista": "Rapsusklei", "album": "Restos y Rarezas 3", "año": 2005, "portada": null, "generos": null, "estilos": null, "pais": null, "discogs_id": null, "tracks": [{"num": 1, "titulo": "Intro (Restos y rarezas)", "duracion": 104, "videoId": "bmZNtNlJqZQ"}, {"num": 2, "titulo": "Ventiuna líneas", "duracion": 90, "videoId": null}, {"num": 3, "titulo": "Zaragoza ciudad de leones", "duracion": 267, "videoId": "v2UplbWrrGI"}, {"num": 4, "titulo": "Odio", "duracion": 169, "videoId": null}, {"num": 5, "titulo": "Dónde está ese banco", "duracion": 119, "videoId": null}, {"num": 6, "titulo": "A veces", "duracion": 247, "videoId": null}, {"num": 7, "titulo": "Pirata", "duracion": 255, "videoId": "WHpgL_vVZZM"}, {"num": 8, "titulo": "Interludio (Inthahouse Mix)", "duracion": 44, "videoId": "EDPn48SyM1M"}, {"num": 9, "titulo": "Gloria sin soledad", "duracion": 153, "videoId": null}, {"num": 10, "titulo": "Interludio (English Sux)", "duracion": 96, "videoId": "0-xSDahoXzU"}, {"num": 11, "titulo": "Capricho", "duracion": 272, "videoId": "Sd23EcVYRsI"}, {"num": 12, "titulo": "Porque sueño", "duracion": 281, "videoId": "riagYt6MMcE"}, {"num": 13, "titulo": "Razarezas", "duracion": 165, "videoId": null}, {"num": 14, "titulo": "Algún que otro recuerdo", "duracion": 197, "videoId": null}, {"num": 15, "titulo": "Fin de la semana", "duracion": 159, "videoId": null}, {"num": 16, "titulo": "Ascua", "duracion": 176, "videoId": null}, {"num": 17, "titulo": "El principio de mis versos", "duracion": 263, "videoId": null}, {"num": 18, "titulo": "Outro", "duracion": 103, "videoId": "bmZNtNlJqZQ"}]}