{"id": 6030, "artista": "Norick", "album": "La Chancadora", "año": 2011, "portada": "https://i.discogs.com/Ynwy8iksNs4Y3HJA_8cjDFcM0PuzA2kWY4j1nc6QCNI/rs:fit/g:sm/q:90/h:600/w:600/czM6Ly9kaXNjb2dz/LWRhdGFiYXNlLWlt/YWdlcy9SLTEwMDc2/NTMyLTE0OTExOTUw/MjYtMTg4Ni5qcGVn.jpeg", "generos": ["Hip Hop"], "estilos": ["Boom Bap", "Conscious"], "pais": "Peru", "discogs_id": 10076532, "tracks": [{"num": 1, "titulo": "Intro", "duracion": 60, "videoId": "JVXDulFY54Y"}, {"num": 2, "titulo": "Portate Bien", "duracion": 297, "videoId": "Q49IxQ18mBs"}, {"num": 3, "titulo": "Asi no era", "duracion": 189, "videoId": "oN1mX4aX-XI"}, {"num": 4, "titulo": "Quien es quien? ft. Murder", "duracion": 181, "videoId": "pl_CzWsThi4"}, {"num": 5, "titulo": "Diferente a los demás", "duracion": 241, "videoId": "3eqVeRYZKF8"}, {"num": 6, "titulo": "Deja de llorar", "duracion": 196, "videoId": "p1FvSyq8EG4"}, {"num": 7, "titulo": "Fuera de la raya ft. La Sky", "duracion": 228, "videoId": "-xQxMUe3-1E"}, {"num": 8, "titulo": "Te equivocaste", "duracion": 245, "videoId": "4WqAEoNo5AA"}, {"num": 9, "titulo": "Nadie Sabe ft. Esteban Clean", "duracion": 214, "videoId": null}, {"num": 10, "titulo": "Inteludio Competencia (Dj Deportado)", "duracion": 73, "videoId": "ltiexkrcaLI"}, {"num": 11, "titulo": "No se me olvida", "duracion": 201, "videoId": "Mb9XpjN_98A"}, {"num": 12, "titulo": "La ultima vez ft. La Prinz", "duracion": 232, "videoId": "yT6-SyLJdI4"}, {"num": 13, "titulo": "No vayas a llorar", "duracion": 216, "videoId": "xC6_9rlL7d4"}, {"num": 14, "titulo": "Que seria?", "duracion": 267, "videoId": "fh1NGth9Qik"}, {"num": 15, "titulo": "Se nos pasa en one ft. Fortuna", "duracion": 267, "videoId": "BYPXMmuFvS0"}, {"num": 16, "titulo": "Habla, cuanto? Ft. Django", "duracion": 296, "videoId": "T3z-hnJpA4c"}, {"num": 17, "titulo": "Reír al ultimo", "duracion": 206, "videoId": "iqRiB-fkm68"}, {"num": 18, "titulo": "Mente Positiva ft. Raper One (OUTRO)", "duracion": 169, "videoId": "k0amnnj0rOI"}]}