{"id": 1458, "artista": "Camarón de la Isla", "album": "Antología", "año": 1996, "portada": null, "generos": null, "estilos": null, "pais": null, "discogs_id": null, "tracks": [{"num": 1, "titulo": "Calle Real (Fandangos a Cané y Valientes de Alonso)", "duracion": 213, "videoId": null}, {"num": 1, "titulo": "Rosa María (Tangos)", "duracion": 138, "videoId": null}, {"num": 1, "titulo": "Detrás del tuyo va (Tangos extremeños)", "duracion": 263, "videoId": null}, {"num": 2, "titulo": "Ná es eterno (Bulerías)", "duracion": 337, "videoId": null}, {"num": 2, "titulo": "Vamos niño pá la bamba (Bambera)", "duracion": 242, "videoId": null}, {"num": 2, "titulo": "Cada vez que nos miramos (Soleares de la Serneta)", "duracion": 229, "videoId": null}, {"num": 3, "titulo": "Caminando (Rumba)", "duracion": 185, "videoId": null}, {"num": 3, "titulo": "Moraíto como un lirio (Tientos)", "duracion": 270, "videoId": null}, {"num": 3, "titulo": "Jardín de belleza (Romeras y Cantiña del contrabandista)", "duracion": 153, "videoId": null}, {"num": 4, "titulo": "Bulerías de La Perla (Bulerías de La Perla de Cádiz)", "duracion": 261, "videoId": null}, {"num": 4, "titulo": "Samara (Bulerías)", "duracion": 208, "videoId": null}, {"num": 4, "titulo": "A los santos del cielo (Seguiriyas de Jerez y los puertos)", "duracion": 250, "videoId": null}, {"num": 5, "titulo": "Yo vivo enamorao (Tangos)", "duracion": 243, "videoId": null}, {"num": 5, "titulo": "Que he dejao de quererte (Granaína)", "duracion": 121, "videoId": null}, {"num": 5, "titulo": "Al Padre Santo de Roma (Tangos)", "duracion": 202, "videoId": null}, {"num": 6, "titulo": "El niño perdido-La cigarra (Bulerías)", "duracion": 429, "videoId": null}, {"num": 6, "titulo": "Y mira que mira y mira (Tangos)", "duracion": 201, "videoId": null}, {"num": 6, "titulo": "El espejo en que te miras (Soleá apolá)", "duracion": 187, "videoId": null}, {"num": 7, "titulo": "Campanas del alba (Seguiriya personal y de Antonio Cagancho)", "duracion": 242, "videoId": null}, {"num": 7, "titulo": "La leyenda del tiempo (Jaleos)", "duracion": 222, "videoId": null}, {"num": 7, "titulo": "Sin motivos ni razón (Fandangos de Macandé)", "duracion": 166, "videoId": null}, {"num": 8, "titulo": "Mar amargo (Alegrías)", "duracion": 211, "videoId": null}, {"num": 8, "titulo": "Romance del Amargo (Bulerías por Soleá)", "duracion": 227, "videoId": null}, {"num": 8, "titulo": "Canastera (Canastera)", "duracion": 232, "videoId": null}, {"num": 9, "titulo": "Viviré (Bulerías)", "duracion": 235, "videoId": null}, {"num": 9, "titulo": "La Tarara (Taranta de la Gabriela, la Taranta y Taranto)", "duracion": 320, "videoId": null}, {"num": 9, "titulo": "Soñaba siempre contigo (Cartagenera de Chacón)", "duracion": 103, "videoId": null}, {"num": 10, "titulo": "Te lo dice Camarón (Rumba)", "duracion": 216, "videoId": null}, {"num": 10, "titulo": "Bahía de Cádiz (Alegrías)", "duracion": 176, "videoId": null}, {"num": 10, "titulo": "Estás ciego pá no ver (Bulería por Soleá)", "duracion": 217, "videoId": null}, {"num": 11, "titulo": "Homenaje a Chaqueta (Soleares del Mellizo y La Andona)", "duracion": 285, "videoId": null}, {"num": 11, "titulo": "Volando voy (Rumba)", "duracion": 205, "videoId": null}, {"num": 11, "titulo": "Sere... Serenito (Canción)", "duracion": 226, "videoId": null}, {"num": 12, "titulo": "Soy gitano (Tangos con Taranto)", "duracion": 257, "videoId": null}, {"num": 12, "titulo": "Un tiro al aire (Alegrías)", "duracion": 286, "videoId": null}, {"num": 12, "titulo": "Caminito de Totana (Taranto)", "duracion": 189, "videoId": null}, {"num": 13, "titulo": "El pez más viejo del río (Fandangos de Gloria)", "duracion": 166, "videoId": null}, {"num": 13, "titulo": "Chiquito de camas (Fandangos de Juan El Camas)", "duracion": 168, "videoId": null}, {"num": 13, "titulo": "Las doce acaban de dar (Toná y Martinete)", "duracion": 140, "videoId": null}, {"num": 14, "titulo": "Dicen de mí (Bulería por Seguiriyas)", "duracion": 277, "videoId": null}, {"num": 14, "titulo": "Limón de cera (Bulerías)", "duracion": 254, "videoId": null}, {"num": 14, "titulo": "A Belén pastores (Villancico)", "duracion": 300, "videoId": null}, {"num": 15, "titulo": "Nana del caballo grande (Nana)", "duracion": 354, "videoId": null}, {"num": 15, "titulo": "Como el agua (Tangos)", "duracion": 223, "videoId": null}, {"num": 15, "titulo": "Qué desgraciaítos son (Tangos)", "duracion": 339, "videoId": null}, {"num": 16, "titulo": "Potro de rabia y miel (Bulerías)", "duracion": 347, "videoId": null}, {"num": 16, "titulo": "Pueblos de la tierra mía (Alegrías)", "duracion": 190, "videoId": null}, {"num": 16, "titulo": "Me dijeron una ocasión (Bulerías)", "duracion": 219, "videoId": null}, {"num": 17, "titulo": "La primavera (Rumba)", "duracion": 235, "videoId": null}, {"num": 17, "titulo": "En tu puerta da la luna (Taranto y Taranta Malagueña de Fernando el de Triana)", "duracion": 267, "videoId": null}, {"num": 17, "titulo": "Ni que me manden a mí (Fandangos de Morente)", "duracion": 250, "videoId": null}, {"num": 18, "titulo": "Toma que toma-Mi barrio-Pa que me llamas prima (Sevillanas)", "duracion": 247, "videoId": null}, {"num": 18, "titulo": "La luz de aquella farola (Bulerías)", "duracion": 204, "videoId": null}, {"num": 18, "titulo": "Arte y Majestad (Bulerías)", "duracion": 180, "videoId": null}]}