{"id": 1507, "artista": "Canserbero", "album": "Margarita (EN VIVO)", "año": 2011, "portada": null, "generos": null, "estilos": null, "pais": null, "discogs_id": null, "tracks": [{"num": 1, "titulo": "LA VOZ (En Vivo)", "duracion": 247, "videoId": null}, {"num": 2, "titulo": "VIDA (En Vivo)", "duracion": 246, "videoId": null}, {"num": 3, "titulo": "EL MUNDO YA SE ACABO (En Vivo)", "duracion": 290, "videoId": null}, {"num": 4, "titulo": "TRIPOLAR (En Vivo)", "duracion": 426, "videoId": null}, {"num": 5, "titulo": "JEREMIAS (En Vivo)", "duracion": 345, "videoId": null}, {"num": 6, "titulo": "PENSANDO EN TI (En Vivo)", "duracion": 246, "videoId": null}, {"num": 7, "titulo": "MAÑANA SERA OTRO DIA (En Vivo)", "duracion": 208, "videoId": null}, {"num": 8, "titulo": "NA (acapella) y EPILOGO (En Vivo)", "duracion": 444, "videoId": null}, {"num": 9, "titulo": "CLIMA TROPICAL (En Vivo)", "duracion": 236, "videoId": null}, {"num": 10, "titulo": "¿Y LA FELICIDAD QUE? (En Vivo)", "duracion": 289, "videoId": null}, {"num": 11, "titulo": "ACEPTAS (En Vivo)", "duracion": 243, "videoId": null}]}