{"id": 1558, "artista": "Carmela", "album": "The Fantastic Carmela Sings Latin American Folklore", "año": 1964, "portada": null, "generos": null, "estilos": null, "pais": null, "discogs_id": null, "tracks": [{"num": 1, "titulo": "El Macon", "duracion": 105, "videoId": null}, {"num": 1, "titulo": "Venezuela: El macan", "duracion": 188, "videoId": null}, {"num": 2, "titulo": "Peru: De terciopelo negro", "duracion": 180, "videoId": null}, {"num": 3, "titulo": "Peru: Que nadie sepa mi sufrir", "duracion": 173, "videoId": null}, {"num": 4, "titulo": "Venezuela: La chipola", "duracion": 109, "videoId": null}, {"num": 5, "titulo": "Peru: Estrellita del sur", "duracion": 140, "videoId": null}, {"num": 6, "titulo": "Mexico: Flor silvestre", "duracion": 223, "videoId": null}, {"num": 7, "titulo": "Columbia: Silverio", "duracion": 122, "videoId": null}, {"num": 8, "titulo": "Venezuela: Madrugada llanera", "duracion": 115, "videoId": null}, {"num": 9, "titulo": "Ecuador: Hojos que lleva el viento", "duracion": 146, "videoId": null}, {"num": 10, "titulo": "Venezuela: Partida", "duracion": 137, "videoId": null}, {"num": 11, "titulo": "Bolivia: Naranjita", "duracion": 132, "videoId": null}, {"num": 12, "titulo": "Venezuela: Brumas del mair", "duracion": 147, "videoId": null}, {"num": 13, "titulo": "Argentina: Zambita arrivena", "duracion": 173, "videoId": null}, {"num": 14, "titulo": "Venezuela: Guerra de los vargas", "duracion": 100, "videoId": null}]}