{"id": 9404, "artista": "Various Artists", "album": "[Unknown Album]", "año": null, "portada": null, "generos": null, "estilos": null, "pais": null, "discogs_id": null, "tracks": [{"num": -1, "titulo": "", "duracion": 3970, "videoId": "jb5F_blSsM8"}, {"num": -1, "titulo": "'S MIX -", "duracion": 4796, "videoId": "-jPd5Dp_3F8"}, {"num": -1, "titulo": "80S MSK FRESKA BY DJ JAVI", "duracion": 3754, "videoId": null}, {"num": -1, "titulo": "A.C.T.V- SpooK - Chocolate - Puzzle - Barraca RemmebeR 90", "duracion": 4912, "videoId": null}, {"num": -1, "titulo": "LUIS REMEMBER VOL 3", "duracion": 4912, "videoId": "nqUQE1XGlrk"}, {"num": -1, "titulo": "A 3 PLATOS SPOOK & CHOCOLA", "duracion": 4474, "videoId": null}, {"num": -1, "titulo": "Dj Salvaje - sesion remember (homenaje a psicodromo y dixkontrol)", "duracion": 1916, "videoId": "O9a1k1WQa6U"}, {"num": -1, "titulo": "www.elquemestrenca.net", "duracion": 5583, "videoId": null}, {"num": -1, "titulo": "Entrevista a Fran Leaners", "duracion": 1546, "videoId": "IKBSlJlNu7c"}, {"num": -1, "titulo": "Hacienda 12-01-91", "duracion": 5532, "videoId": "aZXZxO3Y9lM"}, {"num": -1, "titulo": "This Is Tech-Pop: 21st Century Electro And New Wave", "duracion": 4636, "videoId": null}, {"num": -1, "titulo": "Rayate - Baile Mix", "duracion": 1238, "videoId": null}, {"num": -1, "titulo": "Sesion%20Raul%20Platero[1]", "duracion": 2018, "videoId": null}, {"num": -1, "titulo": "Freezepop / Plastic Stars", "duracion": 234, "videoId": "0e4eru8Kr3g"}, {"num": -1, "titulo": "dj gus vol 16.000", "duracion": 4159, "videoId": null}, {"num": -1, "titulo": "progressive by dj marta", "duracion": 3989, "videoId": null}, {"num": -1, "titulo": "sonidoValencia_1de6_82-92_Barraca_Chocolate_Spook_Espiral_Puzzle_ACTV_NOD", "duracion": 4796, "videoId": null}, {"num": 1, "titulo": "Dj Javi-Level - House - Valls TGN - 29.11.2003", "duracion": 4280, "videoId": null}, {"num": 1, "titulo": "Las Mejores cantaditas de la Llamada RUTA DEL BAKALAO", "duracion": 4277, "videoId": null}, {"num": 1, "titulo": "SESIONACA CANTADOS vs BASES AÑOS 90 - DJ FRAN BP- SANTA POLA", "duracion": 3773, "videoId": null}, {"num": 9, "titulo": "FPU / Ocean Drive (Tigas White", "duracion": 289, "videoId": null}]}