{"id": 9825, "artista": "Various Artists", "album": "Soul Vocal Group Delights, Vol. 1", "año": null, "portada": null, "generos": null, "estilos": null, "pais": null, "discogs_id": null, "tracks": [{"num": 1, "titulo": "Wherever You Go", "duracion": 273, "videoId": "YMo8zSQBfRE"}, {"num": 2, "titulo": "Misty", "duracion": 191, "videoId": "0gbRZAn2tcg"}, {"num": 3, "titulo": "Take It Slow", "duracion": 247, "videoId": "wR7MONw2Fbc"}, {"num": 4, "titulo": "Can This Be Real", "duracion": 205, "videoId": "Ha6F9xDCjIE"}, {"num": 5, "titulo": "God Bless Our Love", "duracion": 179, "videoId": "tUQ2sJnlUOI"}, {"num": 6, "titulo": "To Be Or Not To Be", "duracion": 178, "videoId": "PKBImKAZlG0"}, {"num": 7, "titulo": "Country Girl", "duracion": 228, "videoId": "r7A0Sjiu2zg"}, {"num": 8, "titulo": "Your Love", "duracion": 238, "videoId": "fTsz1LggpcQ"}, {"num": 9, "titulo": "Never No More", "duracion": 149, "videoId": "y-jebaV3ZlA"}, {"num": 10, "titulo": "That's What Girls Are Made For", "duracion": 186, "videoId": "oKLQU7XUOYI"}, {"num": 11, "titulo": "How Can I Pretend", "duracion": 177, "videoId": "bxtriAqdkno"}, {"num": 12, "titulo": "Hey There Lonely Boy", "duracion": 170, "videoId": "0tSpZnVnSLQ"}, {"num": 13, "titulo": "A Million To One", "duracion": 203, "videoId": "uZ5pxPWvM88"}, {"num": 14, "titulo": "I Wanna Know Right Now", "duracion": 193, "videoId": "pqrUQrAcfo4"}, {"num": 15, "titulo": "Don't Stop Now", "duracion": 163, "videoId": "LYySsU8A08w"}, {"num": 16, "titulo": "My Hero", "duracion": 159, "videoId": "ObRSC8HXr3M"}]}