{"id": 10657, "artista": "Various Artists", "album": "Death Proof", "año": 2007, "portada": "https://i.discogs.com/L1uxN5xaT2ilD0jZZPJja1vYKmUoCCV3_XWAwOpoMts/rs:fit/g:sm/q:90/h:600/w:580/czM6Ly9kaXNjb2dz/LWRhdGFiYXNlLWlt/YWdlcy9SLTY0Nzk2/MjMtMTQ2NzI5OTY1/NC0yNTU4LmpwZWc.jpeg", "generos": ["Electronic"], "estilos": ["Dubstep"], "pais": "Europe", "discogs_id": 6479623, "tracks": [{"num": 1, "titulo": "The Last Race", "duracion": 160, "videoId": "Yb4Obd9u9K4"}, {"num": 2, "titulo": "Baby It’s You", "duracion": 203, "videoId": "wTu3SaIcZSc"}, {"num": 3, "titulo": "Paranoia prima", "duracion": 200, "videoId": "DU4nipmf3uU"}, {"num": 4, "titulo": "Planning & Scheming", "duracion": 61, "videoId": "Pj9u1RWMAdU"}, {"num": 5, "titulo": "Jeepster", "duracion": 249, "videoId": "IQc-uPOBA5o"}, {"num": 6, "titulo": "Stuntman Mike", "duracion": 19, "videoId": "fkwYqQrPLAc"}, {"num": 7, "titulo": "Staggolee", "duracion": 231, "videoId": "n9miEWUBYpg"}, {"num": 8, "titulo": "The Love You Save (May Be Your Own)", "duracion": 177, "videoId": "IFIx0K2vpT4"}, {"num": 9, "titulo": "Good Love, Bad Love", "duracion": 131, "videoId": "MJHkXLaJwU4"}, {"num": 10, "titulo": "Down in Mexico", "duracion": 203, "videoId": null}, {"num": 11, "titulo": "Hold Tight", "duracion": 167, "videoId": "4JyE7IrPmjw"}, {"num": 12, "titulo": "Sally and Jack", "duracion": 86, "videoId": null}, {"num": 13, "titulo": "It’s So Easy", "duracion": 131, "videoId": "eAUanpuwOlk"}, {"num": 14, "titulo": "Whatever-However", "duracion": 36, "videoId": "fo3T8eDGZdA"}, {"num": 15, "titulo": "Riot in Thunder Alley", "duracion": 124, "videoId": "aXvEXdKtD6M"}, {"num": 16, "titulo": "Chick Habit", "duracion": 127, "videoId": "iDeoYk7oxN4"}]}