{"id": 10692, "artista": "Various Artists", "album": "El Rock Català: 1993", "año": 2008, "portada": "https://i.discogs.com/c-gYF9PKxGKXENojHYntGM8UoPeHdzVB1eCkwKb9_lU/rs:fit/g:sm/q:90/h:600/w:445/czM6Ly9kaXNjb2dz/LWRhdGFiYXNlLWlt/YWdlcy9SLTEzOTQx/NTM3LTE1NjQ1ODc3/ODYtMzMwOC5qcGVn.jpeg", "generos": ["Electronic", "Jazz", "Rock", "Pop"], "estilos": ["Jazz-Rock"], "pais": "Spain", "discogs_id": 13941537, "tracks": [{"num": 1, "titulo": "És inútil continuar", "duracion": 284, "videoId": "1QxO6-O-dHI"}, {"num": 2, "titulo": "Freddie Memorium", "duracion": 262, "videoId": "vLPWSBLjypA"}, {"num": 3, "titulo": "Stella Splendens", "duracion": 244, "videoId": "XrqZsyDiuMI"}, {"num": 4, "titulo": "S'ha fet gran", "duracion": 284, "videoId": "EIUMD5uoDC0"}, {"num": 5, "titulo": "Més que la meva sang", "duracion": 212, "videoId": "D_CU4lfvmnM"}, {"num": 6, "titulo": "Repapiejant", "duracion": 187, "videoId": "JkXGI0BQ5L8"}, {"num": 7, "titulo": "Fidels a la utopia", "duracion": 208, "videoId": "VHALeiwpJrc"}, {"num": 8, "titulo": "La balada de la banda del bar", "duracion": 271, "videoId": "e4lE_Wvi54E"}, {"num": 9, "titulo": "Foc al cor", "duracion": 285, "videoId": "yBSgx3zqRLM"}, {"num": 10, "titulo": "Nits de juliol a Sant Feliu", "duracion": 172, "videoId": null}, {"num": 11, "titulo": "L'exprés de mitjanit", "duracion": 244, "videoId": "m95Frr9DtZo"}, {"num": 12, "titulo": "Torna a ser massa tard", "duracion": 245, "videoId": "WU0mxroIPGk"}, {"num": 13, "titulo": "La casa del llum vermell", "duracion": 264, "videoId": "eFKWMNJjuLc"}, {"num": 14, "titulo": "Vivint sense tu", "duracion": 261, "videoId": "tJFcAoA3oqY"}, {"num": 15, "titulo": "Tu mateix", "duracion": 208, "videoId": "gg1izKpSacY"}, {"num": 16, "titulo": "Quan l'alcohol deforma", "duracion": 174, "videoId": null}, {"num": 17, "titulo": "No els deixem tornar", "duracion": 260, "videoId": "HjUusp1uCDE"}, {"num": 18, "titulo": "Free Hands", "duracion": 212, "videoId": "gpUJOJWYbvA"}]}