{"id":10729,"artista":"Various Artists","album":"Lux & Ivy's Favorites, Volume 1","año":2009,"portada":"https://lastfm.freetls.fastly.net/i/u/300x300/5f084c6fd7bb4e27ce08eaf10787886c.jpg","generos":null,"estilos":null,"pais":null,"discogs_id":null,"tracks":[{"num":1,"titulo":"Shombalor","duracion":138,"videoId":"MEhnizxC290"},{"num":2,"titulo":"Let 'Er Rip","duracion":156,"videoId":"_YDnb_sAafg","fuente":"curador"},{"num":3,"titulo":"Bluebirds Over the Mountain","duracion":92,"videoId":"akXU5n6AR1I","fuente":"curador"},{"num":4,"titulo":"Hangin' Around","duracion":147,"videoId":"Bj8AThi7_q8","fuente":"curador"},{"num":5,"titulo":"Action Packed","duracion":136,"videoId":"eJsHF1D1PD0"},{"num":6,"titulo":"Date Bait","duracion":139,"videoId":"FKNKumFXkNg","fuente":"curador"},{"num":7,"titulo":"Bop Crazy Baby","duracion":104,"videoId":"IlOIE3QiSYw","fuente":"curador"},{"num":8,"titulo":"Death of an Angel","duracion":191,"videoId":"Ye2OGW76HgE","fuente":"curador"},{"num":9,"titulo":"Crazy Baby","duracion":123,"videoId":"HpkMXbEbUXY","fuente":"curador"},{"num":10,"titulo":"The Bells","duracion":199,"videoId":"9i5XVH_Pa7k","fuente":"curador"},{"num":11,"titulo":"The Mummy","duracion":123,"videoId":"WhuRWFkAdFA"},{"num":12,"titulo":"RFD Ragoon","duracion":124,"videoId":"f6tn5AeKzD4"},{"num":13,"titulo":"Enchanted Farm","duracion":119,"videoId":"UY_It9qf1IA"},{"num":14,"titulo":"Behind the Door","duracion":194,"videoId":"NIa8tE5NjH8"},{"num":15,"titulo":"Transfusion","duracion":149,"videoId":"NOWxY4EFaVQ"},{"num":16,"titulo":"Crawlin'","duracion":158,"videoId":"I6NU3kWqnDE"},{"num":17,"titulo":"Earth Angel","duracion":182,"videoId":"66rK3Gmln74"},{"num":18,"titulo":"Don't Fuck Around With Love","duracion":176,"videoId":"MgT80H8EQ14"},{"num":19,"titulo":"Skull and Crossbones","duracion":157,"videoId":"f96r5-v7W0o"},{"num":20,"titulo":"Bila","duracion":136,"videoId":"Aun_TFe3Up8"},{"num":21,"titulo":"Tight Skirt Tight Sweater","duracion":134,"videoId":"Ya9pfDPLK9M"},{"num":22,"titulo":"Telstar","duracion":201,"videoId":"N11I543_0n4"},{"num":23,"titulo":"Poon Tang","duracion":159,"videoId":"FICt1jsuvn4"},{"num":24,"titulo":"Rotten Cocksuckers Ball","duracion":83,"videoId":"hQ3kIheNqVs"},{"num":25,"titulo":"Whistle Bait","duracion":98,"videoId":"xIJiOCp64MI"},{"num":26,"titulo":"Rubber Buscuit","duracion":128,"videoId":"Obiw1lhs_bo"},{"num":27,"titulo":"Jennie Lee","duracion":125,"videoId":"vSAxUNIIWe4"}]}