{"id": 7769, "artista": "Terbutalina", "album": "Broncodilatador", "año": 2011, "portada": "https://lastfm.freetls.fastly.net/i/u/300x300/0c27958e35dd4a8eb1e8699236cc04ea.png", "generos": null, "estilos": null, "pais": null, "discogs_id": null, "tracks": [{"num": 1, "titulo": "Helipuerto", "duracion": 66, "videoId": null}, {"num": 2, "titulo": "Cartos", "duracion": 70, "videoId": null}, {"num": 3, "titulo": "Filloa", "duracion": 132, "videoId": null}, {"num": 4, "titulo": "Canto moderno", "duracion": 78, "videoId": null}, {"num": 5, "titulo": "Espija", "duracion": 93, "videoId": null}, {"num": 6, "titulo": "A historia de Bola", "duracion": 82, "videoId": "WFmSWl1EJ8w"}, {"num": 7, "titulo": "Juapo", "duracion": 144, "videoId": null}, {"num": 8, "titulo": "Madeleine", "duracion": 48, "videoId": "O9sQ94YYkFw"}, {"num": 9, "titulo": "R.A.J.O.Y.", "duracion": 75, "videoId": "9FNHks3JqFQ"}, {"num": 10, "titulo": "Cura de la hostia", "duracion": 97, "videoId": "DM_Uijpfams"}, {"num": 11, "titulo": "Rubia", "duracion": 96, "videoId": "xwvCgWmB_X4"}, {"num": 12, "titulo": "Peneira", "duracion": 133, "videoId": "EbRoA8T0QLQ"}, {"num": 13, "titulo": "Carallo", "duracion": 43, "videoId": null}, {"num": 14, "titulo": "Cheiras ao bravo", "duracion": 123, "videoId": "Ycmxk_z_4Zg"}, {"num": 15, "titulo": "Acabar co nejro (OST)", "duracion": 100, "videoId": null}]}