{"id": 8921, "artista": "Tryo", "album": "Faut qu’ils s’activent", "año": 2000, "portada": "https://i.discogs.com/aPxt5pfWPaHPePSt0PyO1halqhTmS094Ahks5NWOHsU/rs:fit/g:sm/q:90/h:600/w:448/czM6Ly9kaXNjb2dz/LWRhdGFiYXNlLWlt/YWdlcy9SLTI5MTM5/NDEtMTM5MDU4MDg2/MC0yOTM2LmpwZWc.jpeg", "generos": ["Reggae"], "estilos": ["Reggae-Pop"], "pais": "France", "discogs_id": 2913941, "tracks": [{"num": 1, "titulo": "J’ai trouvé des amis", "duracion": 286, "videoId": "TZmYzM-vIgY"}, {"num": 2, "titulo": "Le Petit Chose", "duracion": 177, "videoId": "ruQ5X6kHt4U"}, {"num": 3, "titulo": "Con par raison", "duracion": 248, "videoId": "kCQRRy3H-YU"}, {"num": 4, "titulo": "Plus on en fait", "duracion": 209, "videoId": "dHAxI2YnDrE"}, {"num": 5, "titulo": "Paris", "duracion": 348, "videoId": "j_BTDunsn4w"}, {"num": 6, "titulo": "Les Extrêmes", "duracion": 164, "videoId": "EtgP8Tvj6_A"}, {"num": 7, "titulo": "Cinq sens", "duracion": 281, "videoId": "J8wLX-np85o"}, {"num": 8, "titulo": "La Mer", "duracion": 211, "videoId": "hGORspM8euI"}, {"num": 9, "titulo": "La Débandade", "duracion": 144, "videoId": "qjYKM3ZZcm4"}, {"num": 10, "titulo": "Les Nouveaux Bergers", "duracion": 278, "videoId": "qW9jAHFkREA"}, {"num": 11, "titulo": "Le monde est avare", "duracion": 409, "videoId": "vdby7FHNGus"}, {"num": 12, "titulo": "Ça y est c’est fait", "duracion": 176, "videoId": "ZRbM1m9hKYM"}, {"num": 13, "titulo": "Le Saule", "duracion": 313, "videoId": "lhjzGKqouGg"}, {"num": 14, "titulo": "La Lumière", "duracion": 931, "videoId": "nfy2wMuFSgA"}]}