{"id": 7532, "artista": "Squirrel Nut Zippers", "album": "Hot", "año": 1996, "portada": "https://i.discogs.com/08jKgCBohC_bo0DNpoTHyiAcwmeLxxQDQlGvXOCL20k/rs:fit/g:sm/q:90/h:459/w:600/czM6Ly9kaXNjb2dz/LWRhdGFiYXNlLWlt/YWdlcy9SLTUxNzY2/MzUtMTYwODMyMjMx/NC05MjYzLmpwZWc.jpeg", "generos": ["Jazz"], "estilos": ["Ragtime", "Swing"], "pais": "UK & US", "discogs_id": 5176635, "tracks": [{"num": 1, "titulo": "Got My Own Thing Now", "duracion": 151, "videoId": "2za-wgmPqHI"}, {"num": 2, "titulo": "Put a Lid on It", "duracion": 159, "videoId": "wFzjkeKd2Ts"}, {"num": 3, "titulo": "Memphis Exorcism", "duracion": 145, "videoId": "mCuKHTcO1-E"}, {"num": 4, "titulo": "Twilight", "duracion": 215, "videoId": "3rbm3NguGZY"}, {"num": 5, "titulo": "It Ain't You", "duracion": 188, "videoId": "e04m1Zu9Dt0"}, {"num": 6, "titulo": "Prince Nez", "duracion": 174, "videoId": "vhnJlpj2Iak"}, {"num": 7, "titulo": "Hell", "duracion": 193, "videoId": "gFw5japDG2U"}, {"num": 8, "titulo": "Meant to Be", "duracion": 192, "videoId": "ZadGGGlmemA"}, {"num": 9, "titulo": "Bad Businessman", "duracion": 229, "videoId": "uknbM3yyNvw"}, {"num": 10, "titulo": "Flight of the Passing Fancy", "duracion": 232, "videoId": "mmW0KesBsP4"}, {"num": 11, "titulo": "Blue Angel", "duracion": 275, "videoId": "Vco-5bF690c"}, {"num": 12, "titulo": "The Interlocutor", "duracion": 168, "videoId": "Y28LHEgHP2M"}]}