{"id": 7649, "artista": "Suma Paciencia", "album": "Suma Paciencia", "año": 2016, "portada": null, "generos": null, "estilos": null, "pais": null, "discogs_id": null, "tracks": [{"num": 1, "titulo": "Celebra (Inv. Pablo Molina)", "duracion": 287, "videoId": null}, {"num": 2, "titulo": "Depende de miI (Inv. Hugo Lobo)", "duracion": 292, "videoId": "AqhrtQmN0yE"}, {"num": 3, "titulo": "Lirica en prosa", "duracion": 215, "videoId": "79ZsUWjfom4"}, {"num": 4, "titulo": "Todos buscamos", "duracion": 214, "videoId": "M4EpkeNUHQw"}, {"num": 5, "titulo": "Te callas", "duracion": 414, "videoId": "CCbn9msN81c"}, {"num": 6, "titulo": "Sin darte cuenta", "duracion": 305, "videoId": "tO-Oyq3L9DQ"}, {"num": 7, "titulo": "Ambición", "duracion": 222, "videoId": "-ZFAC61EL-k"}]}