{"id": 3362, "artista": "Herbie Hancock", "album": "The Essence", "año": 2001, "portada": "https://i.discogs.com/JHdyex6-PfoJwmNrDK30P1bkw16JgtBeHQfcbo2Zm-0/rs:fit/g:sm/q:90/h:600/w:600/czM6Ly9kaXNjb2dz/LWRhdGFiYXNlLWlt/YWdlcy9SLTE1Mzg3/LTE1NTk2OTg5OTkt/ODE4Ni5qcGVn.jpeg", "generos": ["Electronic"], "estilos": ["Drum n Bass", "Abstract", "Acid Jazz", "Downtempo"], "pais": "US", "discogs_id": 15387, "tracks": [{"num": 1, "titulo": "The Essence (LTJ Bukem’s DJ mix)", "duracion": 550, "videoId": "ELmhGNNNHts"}, {"num": 2, "titulo": "The Essence (Extra Go dub)", "duracion": 384, "videoId": "ELmhGNNNHts"}, {"num": 3, "titulo": "The Essence (DJ Krush main mix)", "duracion": 347, "videoId": "ELmhGNNNHts"}, {"num": 4, "titulo": "The Essence (Future 2 Future album mix)", "duracion": 292, "videoId": "ELmhGNNNHts"}]}