{"id": 8233, "artista": "The Hollies", "album": "Live at the BBC", "año": 2018, "portada": "https://i.discogs.com/JHOrLTyXN8b6CmTZ16Mat-op1zeDl9dCmwchbfaO6Bk/rs:fit/g:sm/q:90/h:600/w:600/czM6Ly9kaXNjb2dz/LWRhdGFiYXNlLWlt/YWdlcy9SLTEyODA2/MDM3LTE1NDIzMDg0/ODQtNzU4Mi5qcGVn.jpeg", "generos": ["Rock", "Pop"], "estilos": ["Rock & Roll", "Beat"], "pais": "Europe", "discogs_id": 12806037, "tracks": [{"num": 1, "titulo": "Here I Go Again (BBC Live Session)", "duracion": 136, "videoId": "PoBgDzVmml4"}, {"num": 2, "titulo": "Jennifer Eccles (BBC Live Session)", "duracion": 161, "videoId": "z_NlECP3cZo"}, {"num": 3, "titulo": "I've Got a Way of My Own (BBC Live Session)", "duracion": 125, "videoId": "DCat13VDVD4"}, {"num": 4, "titulo": "Wings (BBC Live Session)", "duracion": 181, "videoId": "vzZtvEg1dbA"}, {"num": 5, "titulo": "Step Inside (BBC Live Session)", "duracion": 165, "videoId": "nkk6n9W2J_o"}, {"num": 6, "titulo": "Shake (BBC Live Session)", "duracion": 131, "videoId": "uW4iU8GLmKs"}, {"num": 7, "titulo": "I Take What I Want (BBC Live Session)", "duracion": 150, "videoId": "5h05JDEZhCY"}, {"num": 8, "titulo": "Away Away Away (BBC Live Session)", "duracion": 123, "videoId": "XMUBWxWUCKQ"}, {"num": 9, "titulo": "Charlie and Fred (BBC Live Session)", "duracion": 165, "videoId": "Yhk2Z5gTeIw"}, {"num": 10, "titulo": "Something's Got a Hold On Me (BBC Live Session)", "duracion": 176, "videoId": "zeRh-N9JeVc"}, {"num": 11, "titulo": "Nobody (BBC Live Session)", "duracion": 158, "videoId": "FRRl7hS6TjM"}, {"num": 12, "titulo": "Set Me Free (BBC Live Session)", "duracion": 115, "videoId": "OPmxxbvN7_0"}, {"num": 13, "titulo": "She Said Yeah (BBC Live Session)", "duracion": 111, "videoId": "BQkL-pR7R7Q"}, {"num": 14, "titulo": "You Must Believe Me (BBC Live Session)", "duracion": 125, "videoId": "UYKIMLijNBw"}, {"num": 15, "titulo": "Too Many People (BBC Live Session)", "duracion": 160, "videoId": "hTn9MUTpoYw"}, {"num": 16, "titulo": "Look Through Any Window (BBC Live Session)", "duracion": 132, "videoId": "MlwL_rPi9xA"}, {"num": 17, "titulo": "Too Young to Be Married (BBC Live Session)", "duracion": 253, "videoId": "_AVqc0ABv0c"}, {"num": 18, "titulo": "I'm Alive (BBC Live Session)", "duracion": 141, "videoId": "JCy2mjz0g24"}, {"num": 19, "titulo": "The Games We Play (BBC Live Session)", "duracion": 161, "videoId": "yvFcTc_Rc5Q"}, {"num": 20, "titulo": "He Ain't Heavy He's My Brother (BBC Live Session)", "duracion": 252, "videoId": "jVuBzfZDBNY"}]}