{"id":4151,"artista":"Kase.O","album":"Dentro del círculo","año":2019,"portada":"https://i.discogs.com/g5VPi1H9qHrYAFLs_y1YlaQUyDiBVV7BNWSnoCHVVng/rs:fit/g:sm/q:90/h:456/w:600/czM6Ly9kaXNjb2dz/LWRhdGFiYXNlLWlt/YWdlcy9SLTE0NDYy/NDIwLTE1NzUwMzAx/NDAtMjY3OC5qcGVn.jpeg","generos":["Hip Hop"],"estilos":null,"pais":"Spain","discogs_id":14462420,"tracks":[{"num":1,"titulo":"Intro","duracion":324,"videoId":"c2Mvs9HtOfc","fuente":"curador"},{"num":2,"titulo":"Esto no para","duracion":250,"videoId":"Q8nV1jl1chg","fuente":"curador"},{"num":3,"titulo":"Yemen","duracion":258,"videoId":"uEM6tcnEYBE","fuente":"curador"},{"num":4,"titulo":"Triste","duracion":150,"videoId":"jhvh_UsHKjU","fuente":"curador"},{"num":5,"titulo":"Guapo tarde","duracion":297,"videoId":"f9VLHi6C9Ro","fuente":"curador"},{"num":6,"titulo":"Pura droga sin cortar","duracion":161,"videoId":"MpWM4GxHE1s","fuente":"curador"},{"num":7,"titulo":"Ninguna chavala tiene dueño","duracion":110,"videoId":"SaPQOkBxJ60","fuente":"curador"},{"num":8,"titulo":"Amor sin cláusulas","duracion":282,"videoId":"J_6Q6tqM14M","fuente":"curador"},{"num":9,"titulo":"Acapella racismo","duracion":23,"videoId":"Rn3XzxSF75c","fuente":"curador"},{"num":10,"titulo":"Boogalo","duracion":220,"videoId":"6P2rZYo_0JU"},{"num":11,"titulo":"Acapella el momo","duracion":74,"videoId":"TFar-_GHrRg"},{"num":12,"titulo":"No sé qué voy a hacer (Booty Song)","duracion":219,"videoId":"WakC0aT2GI8"},{"num":13,"titulo":"Mitad y mitad","duracion":352,"videoId":"alEgAy5OigY"},{"num":14,"titulo":"Viejos ciegos","duracion":436,"videoId":"8VrIuAcz5g4"},{"num":15,"titulo":"Repartiendo arte","duracion":280,"videoId":"jrEMKjdIAmg"},{"num":16,"titulo":"Basureta","duracion":379,"videoId":"IWlkn2NaNNI"}]}