{"id": 162, "artista": "Air", "album": "Air 4: Elle a du shell", "año": 1999, "portada": "https://i.discogs.com/i-ZEgdlSlsJyi8hTYBIkr1fOJd6XKQZjkaCV-RnMdYw/rs:fit/g:sm/q:90/h:348/w:349/czM6Ly9kaXNjb2dz/LWRhdGFiYXNlLWlt/YWdlcy9SLTM1MzYz/OC0xMTAxNDgwODEy/LmpwZw.jpeg", "generos": ["Electronic"], "estilos": ["Ambient"], "pais": "Germany", "discogs_id": 353638, "tracks": [{"num": 1, "titulo": "La Nuit de Tous Nos Rêves Approche", "duracion": 409, "videoId": "vL9uqu_LaTU"}, {"num": 2, "titulo": "Clearing Your Head", "duracion": 493, "videoId": "4IGxDvRAPvA"}, {"num": 3, "titulo": "On Her Way In", "duracion": 564, "videoId": "UE0laNAx--Y"}, {"num": 4, "titulo": "Elle a Du Shell", "duracion": 345, "videoId": "7XGBlNQTliE"}, {"num": 5, "titulo": "Synthetique Be-Bop", "duracion": 140, "videoId": "-Ygi-oeRp_E"}]}