{"id": 329, "artista": "Alfie Shepherd", "album": "The Wind In The Willows", "año": 1969, "portada": "https://i.discogs.com/QMV0KxTHBO5mnLqchBN4bzS_dYXT-SY6MSgr4UDvm-0/rs:fit/g:sm/q:90/h:593/w:600/czM6Ly9kaXNjb2dz/LWRhdGFiYXNlLWlt/YWdlcy9SLTEyNjAw/OTg0LTE2MjgyNDc4/MDEtODgxMC5qcGVn.jpeg", "generos": ["Rock", "Pop", "Folk, World, & Country"], "estilos": ["Psychedelic Rock", "Folk Rock", "Lo-Fi"], "pais": "UK", "discogs_id": 12600984, "tracks": [{"num": 1, "titulo": "Spring Fever", "duracion": 137, "videoId": "3jqTiSgIM6c"}, {"num": 2, "titulo": "Floating On A Dream", "duracion": 239, "videoId": "ytQ27XkV26k"}, {"num": 3, "titulo": "The Wild Wood", "duracion": 260, "videoId": "vVghKCXVIdo"}, {"num": 4, "titulo": "Dulce Domum", "duracion": 190, "videoId": "Nq8KbZBLPR4"}, {"num": 5, "titulo": "The Piper At The Gates Of Dawn", "duracion": 251, "videoId": "goJ178ulcIU"}, {"num": 6, "titulo": "The Open Road", "duracion": 220, "videoId": "fxKgVBz5GeM"}, {"num": 7, "titulo": "Lost In His Life", "duracion": 206, "videoId": "5immV3yWPus"}, {"num": 8, "titulo": "Bargin'", "duracion": 221, "videoId": null}, {"num": 9, "titulo": "The Call Of The South", "duracion": 157, "videoId": "FRIIi3soHQE"}, {"num": 10, "titulo": "\"Like Summer Tempests Came His Tears\"", "duracion": 133, "videoId": "ByytBt4NQqg"}, {"num": 11, "titulo": "The Return Of Ulysses", "duracion": 229, "videoId": "mhxhwXsfjGg"}, {"num": 12, "titulo": "I'm Only The Postman [Bonus Track]", "duracion": 192, "videoId": "HI7jmLvg4QA"}, {"num": 13, "titulo": "Tomorrow's Dreams Today [Bonus Track]", "duracion": 192, "videoId": "8xK38vkpRuE"}, {"num": 14, "titulo": "The Swallow's Song [Bonus Track]", "duracion": 229, "videoId": "WHTSGgKmQIQ"}, {"num": 15, "titulo": "Sandy's Song [Bonus Track]", "duracion": 231, "videoId": null}, {"num": 16, "titulo": "Won't Be Loving Again [Bonus Track]", "duracion": 271, "videoId": "all0T7enkxk"}, {"num": 17, "titulo": "I'm Moving On [Bonus Track]", "duracion": 283, "videoId": "MIC1PXEQ_Yk"}, {"num": 18, "titulo": "Friends [Bonus Track]", "duracion": 149, "videoId": null}, {"num": 19, "titulo": "Sad Statue [Bonus Track]", "duracion": 224, "videoId": "qGOlQuxeikI"}, {"num": 20, "titulo": "Elizabeth Knows [Bonus Track]", "duracion": 290, "videoId": "AcvaSKP587Q"}, {"num": 21, "titulo": "The Resurrection Men [Bonus Track]", "duracion": 229, "videoId": "WBihufI2AfQ"}]}