{"id": 354, "artista": "Alika", "album": "No dejes que te paren", "año": 2000, "portada": "https://i.discogs.com/a380LcN8KSG48kCDID-ygEnuUtxAYCjfkvZNSvgBdCE/rs:fit/g:sm/q:90/h:594/w:600/czM6Ly9kaXNjb2dz/LWRhdGFiYXNlLWlt/YWdlcy9SLTk2Njgy/ODgtMTQ4NDQ3OTY2/Mi02MzA2LmpwZWc.jpeg", "generos": ["Reggae", "Latin"], "estilos": ["Reggae", "Roots Reggae", "Ragga"], "pais": "Argentina", "discogs_id": 9668288, "tracks": [{"num": 1, "titulo": "Intro", "duracion": 60, "videoId": "w4nrKKsokFc"}, {"num": 2, "titulo": "Nueva alianza", "duracion": 242, "videoId": "RAuwDDNWxGk"}, {"num": 3, "titulo": "Aguantare", "duracion": 299, "videoId": "ezySPHXSzgY"}, {"num": 4, "titulo": "Espiritu positivo", "duracion": 294, "videoId": "0Yd-teOI72k"}, {"num": 5, "titulo": "Enemigos", "duracion": 218, "videoId": "ViRIAYpArcw"}, {"num": 6, "titulo": "Ghetto Soul", "duracion": 291, "videoId": "1blF_ekaNxk"}, {"num": 7, "titulo": "No dejes que te paren", "duracion": 357, "videoId": "6aE2VM4LeW4"}, {"num": 8, "titulo": "Sellasie", "duracion": 222, "videoId": "pylpwE-t2EI"}, {"num": 9, "titulo": "Natty Dreadlock", "duracion": 253, "videoId": "Ii0JZcFZGdE"}, {"num": 10, "titulo": "Emprendo El Vuelo", "duracion": 264, "videoId": "NIF7ht6WDKE"}]}