{"id": 498, "artista": "Andy Roberts", "album": "Home Grown", "año": 1970, "portada": "https://i.discogs.com/Sj6fCHQcD4_g1UgoW_tJSKdmhf6-Rr5kYExPUqxinkc/rs:fit/g:sm/q:90/h:227/w:227/czM6Ly9kaXNjb2dz/LWRhdGFiYXNlLWlt/YWdlcy9SLTQyMDUy/MjgtMTM1ODUwNDc3/NC0zMzE5LmpwZWc.jpeg", "generos": ["Rock"], "estilos": ["Folk Rock"], "pais": "UK", "discogs_id": 4205228, "tracks": [{"num": 1, "titulo": "Home Grown", "duracion": 173, "videoId": null}, {"num": 2, "titulo": "Just For The Record", "duracion": 232, "videoId": "3dFQ-c0yr18"}, {"num": 3, "titulo": "Applecross", "duracion": 411, "videoId": "Hi9TYGaDwYQ"}, {"num": 4, "titulo": "The Praties Are Dug", "duracion": 22, "videoId": "YYBxkfkNyvc"}, {"num": 5, "titulo": "John The Revelator", "duracion": 125, "videoId": "A7nEH5F2d-A"}, {"num": 6, "titulo": "Autumn To May", "duracion": 157, "videoId": "P5vNV-Eyo78"}, {"num": 7, "titulo": "Moths And Lizards In Detroit", "duracion": 308, "videoId": "8cg7ZMQaON8"}, {"num": 8, "titulo": "Creepy John", "duracion": 219, "videoId": "-2G2w0tkvfo"}, {"num": 9, "titulo": "Jello", "duracion": 195, "videoId": "2LS016tkw1M"}, {"num": 10, "titulo": "Gig Song", "duracion": 152, "videoId": null}, {"num": 11, "titulo": "Queen Of The Moonlight World", "duracion": 287, "videoId": "IGxnxmNQ0-Q"}, {"num": 12, "titulo": "Where The Soul Of Man Never Dies", "duracion": 177, "videoId": "bS1ltv1VeVg"}, {"num": 13, "titulo": "The One-Armed Boatman And The Giant Squid", "duracion": 360, "videoId": "ENZ8JzB0pGY"}, {"num": 14, "titulo": "Boris At The Organ", "duracion": 102, "videoId": "ZbdzfZ8hl1o"}]}