{"id": 11113, "artista": "White Flag", "album": "R Is For Rocket - U Is For Unreleased", "año": 2003, "portada": "https://i.discogs.com/KBICGnksqGhFQ4dvYtkHhMKElPXPHviO0nkPkpkQOnI/rs:fit/g:sm/q:90/h:361/w:352/czM6Ly9kaXNjb2dz/LWRhdGFiYXNlLWlt/YWdlcy9SLTMwMzc2/NTgtMTMxMjgxNDkz/Ni5qcGVn.jpeg", "generos": ["Rock"], "estilos": ["Punk"], "pais": "US", "discogs_id": 3037658, "tracks": [{"num": 1, "titulo": "Hell in a Handbasket", "duracion": 63, "videoId": null}, {"num": 2, "titulo": "No Such Thing as a Witch", "duracion": 96, "videoId": null}, {"num": 3, "titulo": "Hoppity Hooper", "duracion": 19, "videoId": "X0gcioeopRQ"}, {"num": 4, "titulo": "Mirror, Mirror", "duracion": 111, "videoId": "bzK1MB6BfxM"}, {"num": 5, "titulo": "23 Pieces of Fudge", "duracion": 52, "videoId": null}, {"num": 6, "titulo": "Love Me Like a Reptile", "duracion": 88, "videoId": "HYOCps9GXZ0"}, {"num": 7, "titulo": "I Think I Love You", "duracion": 127, "videoId": "6qW7f6G3Plg"}, {"num": 8, "titulo": "Torture Chamber", "duracion": 109, "videoId": "yrxtgqHJtRc"}, {"num": 9, "titulo": "Paranoid", "duracion": 125, "videoId": "4OwdZaBeE1Q"}, {"num": 10, "titulo": "Cleocin", "duracion": 140, "videoId": null}, {"num": 11, "titulo": "White Flag", "duracion": 50, "videoId": "llSb6q5KlpI"}, {"num": 12, "titulo": "Video D", "duracion": 69, "videoId": null}, {"num": 13, "titulo": "Go to God", "duracion": 53, "videoId": "9sUp4scms9w"}, {"num": 14, "titulo": "R'n'r", "duracion": 89, "videoId": null}, {"num": 15, "titulo": "A Question of Intelligence", "duracion": 110, "videoId": "Jq6YIBt2J-E"}, {"num": 16, "titulo": "Hell in a Handbasket", "duracion": 125, "videoId": null}, {"num": 17, "titulo": "Cleocin", "duracion": 211, "videoId": null}, {"num": 18, "titulo": "Go to God", "duracion": 65, "videoId": "9sUp4scms9w"}, {"num": 19, "titulo": "Mirror, Mirror", "duracion": 129, "videoId": "bzK1MB6BfxM"}, {"num": 20, "titulo": "R'n'r", "duracion": 188, "videoId": null}, {"num": 21, "titulo": "White Flag", "duracion": 50, "videoId": "llSb6q5KlpI"}, {"num": 22, "titulo": "Video.D.", "duracion": 183, "videoId": null}, {"num": 23, "titulo": "Suzy Secret", "duracion": 152, "videoId": "NCY660cdImI"}, {"num": 24, "titulo": "Hell in a Handbasket", "duracion": 155, "videoId": null}, {"num": 25, "titulo": "First Radio Interview May 28, 1982 KUCR, Riverside CA", "duracion": 832, "videoId": null}]}