{"id": 15, "artista": "091", "album": "Tormentas imaginarias", "año": 1993, "portada": "https://i.discogs.com/L6qM5MK6RdtWJIMviaEM46Awh1iFsMj5yN_LMsxSixI/rs:fit/g:sm/q:90/h:600/w:375/czM6Ly9kaXNjb2dz/LWRhdGFiYXNlLWlt/YWdlcy9SLTE3MzAy/MTkyLTE2MTI3MDQ2/NTctNjM2Ni5qcGVn.jpeg", "generos": ["Rock"], "estilos": ["Alternative Rock"], "pais": "Spain", "discogs_id": 17302192, "tracks": [{"num": 1, "titulo": "La calle del viento", "duracion": 271, "videoId": "XQMnXGTF76U"}, {"num": 2, "titulo": "Zapatos de piel de caimán", "duracion": 198, "videoId": "_A1dnS9vNCw"}, {"num": 3, "titulo": "Huellas", "duracion": 220, "videoId": "rEsAfTknYZI"}, {"num": 4, "titulo": "Todo comienza a girar", "duracion": 175, "videoId": "ZQY-6hm_sRE"}, {"num": 5, "titulo": "Sin raíces", "duracion": 246, "videoId": "tribXmpv7uM"}, {"num": 6, "titulo": "Cayendo", "duracion": 166, "videoId": "65cI_0c3PH4"}, {"num": 7, "titulo": "Un cielo color vino", "duracion": 269, "videoId": "ogEsxvrIXoY"}, {"num": 8, "titulo": "Otros como yo", "duracion": 251, "videoId": "-AyifGPRv3k"}, {"num": 9, "titulo": "Para impresionarte", "duracion": 253, "videoId": "4ae7y0Kw0EM"}, {"num": 10, "titulo": "Mi sombra y yo", "duracion": 227, "videoId": "rw4BukrMwC0"}, {"num": 11, "titulo": "Es solo una señal", "duracion": 181, "videoId": "49qupY2fOnI"}, {"num": 12, "titulo": "Tormentas imaginarias", "duracion": 230, "videoId": "M7-UFsvvfSc"}, {"num": 13, "titulo": "El fantasma de la soledad", "duracion": 233, "videoId": "lgZmsD8PCHo"}, {"num": 14, "titulo": "Es hora de enloquecer", "duracion": 327, "videoId": "gkIPE8BLhgk"}]}